livecell_tracker/__init__.py
livecell_tracker/annotation/__init__.py
livecell_tracker/annotation/coco_utils.py
livecell_tracker/annotation/fiftyone_app.py
livecell_tracker/annotation/labelme2coco.py
livecell_tracker/core/__init__.py
livecell_tracker/core/datasets.py
livecell_tracker/core/io_sc.py
livecell_tracker/core/io_utils.py
livecell_tracker/core/napari_visualizer.py
livecell_tracker/core/parallel.py
livecell_tracker/core/sct_operator.py
livecell_tracker/core/single_cell.py
livecell_tracker/core/utils.py
livecell_tracker/core/visualizer.py
livecell_tracker/external/torch_vae/.gitignore
livecell_tracker/external/torch_vae/LICENSE.md
livecell_tracker/external/torch_vae/README.md
livecell_tracker/external/torch_vae/__init__.py
livecell_tracker/external/torch_vae/dataset.py
livecell_tracker/external/torch_vae/experiment.py
livecell_tracker/external/torch_vae/requirements.txt
livecell_tracker/external/torch_vae/run.py
livecell_tracker/external/torch_vae/utils.py
livecell_tracker/external/torch_vae/.idea/.gitignore
livecell_tracker/external/torch_vae/.idea/PyTorch-VAE.iml
livecell_tracker/external/torch_vae/.idea/misc.xml
livecell_tracker/external/torch_vae/.idea/modules.xml
livecell_tracker/external/torch_vae/.idea/vcs.xml
livecell_tracker/external/torch_vae/.idea/inspectionProfiles/profiles_settings.xml
livecell_tracker/external/torch_vae/configs/bbvae.yaml
livecell_tracker/external/torch_vae/configs/betatc_vae.yaml
livecell_tracker/external/torch_vae/configs/bhvae.yaml
livecell_tracker/external/torch_vae/configs/cat_vae.yaml
livecell_tracker/external/torch_vae/configs/cvae.yaml
livecell_tracker/external/torch_vae/configs/dfc_vae.yaml
livecell_tracker/external/torch_vae/configs/dip_vae.yaml
livecell_tracker/external/torch_vae/configs/factorvae.yaml
livecell_tracker/external/torch_vae/configs/gammavae.yaml
livecell_tracker/external/torch_vae/configs/hvae.yaml
livecell_tracker/external/torch_vae/configs/infovae.yaml
livecell-0.0.2.dist-info/entry_points.txt
livecell-0.0.2.dist-info/LICENSE
livecell-0.0.2.dist-info/WHEEL
livecell-0.0.2.dist-info/METADATA
livecell-0.0.2.dist-info/RECORD
